[
  {
    "name": "Media Atom Maker",
    "description": "Making Videos",
    "url": "https://video.gutools.co.uk",
    "github": "https://github.com/guardian/media-atom-maker"
  },
  {
    "name": "Composer",
    "description": "Making Articles",
    "url": "https://composer.gutools.co.uk",
    "github": "https://github.com/guardian/flexible-content"
  },
  {
    "name": "Grid",
    "description": "Managing Images",
    "url": "https://media.gutools.co.uk",
    "github": "https://github.com/guardian/grid",
    "contact": "thegrid.dev@theguardian.com"
  }
]
